{"password":"password123","favourites":[138864,726192,670546,19,474804,866717,784288,492989,640673,429601],"userType":"base","customPOIs":[{"mc":{"floors":[{"name":"Ground Floor","id":0,"pois":[{"posX":1668,"posY":818,"roomNum":28,"favourited":false,"builtIn":false,"name":"Small Men's Washroom","icon":"","id":429601,"type":"Washroom","desc":"Small men's washroom at the right wing of the building. User-created POI for John Doe."}]},{"name":"First Floor","id":1,"pois":[]},{"name":"Second Floor","id":2,"pois":[]},{"name":"Third Floor","id":3,"pois":[]},{"name":"Fourth Floor","id":4,"pois":[]}],"name":"Middlesex College","numFloors":5},"ah":{"floors":[{"name":"Ground Floor","id":0,"pois":[]},{"name":"First Floor","id":1,"pois":[{"posX":711,"posY":1102,"roomNum":122,"favourited":false,"builtIn":false,"name":"Ramp A","icon":"","id":640673,"type":"Navigation","desc":"Small ramp that leads to the mechanical room. User-created POI for John Doe."}]},{"name":"Stage Floor","id":2,"pois":[]}],"name":"Alumni Hall","numFloors":3},"ncb":{"floors":[{"name":"Basement","id":0,"pois":[]},{"name":"First Floor","id":1,"pois":[]},{"name":"Second Floor","id":2,"pois":[{"posX":611,"posY":577,"roomNum":284,"favourited":false,"builtIn":false,"name":"Collab Room A","icon":"","id":670546,"type":"Collaborative Room","desc":"Collaborative Room in the second floor. User created POI for John Doe."}]},{"name":"Third Floor","id":3,"pois":[]},{"name":"Fourth Floor","id":4,"pois":[]}],"name":"North Campus Building","numFloors":5}}],"username":"john_doe"}